gitback/__init__.py
gitback/__main__.py
gitback-1.1.5.data/scripts/git-backup
gitback-1.1.5.dist-info/LICENSE
gitback-1.1.5.dist-info/METADATA
gitback-1.1.5.dist-info/WHEEL
gitback-1.1.5.dist-info/entry_points.txt
gitback-1.1.5.dist-info/top_level.txt
gitback-1.1.5.dist-info/RECORD
