Metadata-Version: 2.1
Name: gitback
Version: 1.1.5
Summary: Makes a backup of all your repositories and gists from GitHub
Home-page: https://github.com/donno2048/gitback
Author: Elisha Hollander
License: MIT
Classifier: Programming Language :: Python :: 3
Requires-Python: >3.8
License-File: LICENSE
